amalgamation_ai/__init__.py
amalgamation_ai/__version__.cpython-312-aarch64-linux-musl.so
amalgamation_ai/_cloud.cpython-312-aarch64-linux-musl.so
amalgamation_ai/_http.cpython-312-aarch64-linux-musl.so
amalgamation_ai/_on_premise.cpython-312-aarch64-linux-musl.so
amalgamation_ai/client.cpython-312-aarch64-linux-musl.so
amalgamation_ai/config.cpython-312-aarch64-linux-musl.so
amalgamation_ai/exceptions.cpython-312-aarch64-linux-musl.so
amalgamation_ai/types.cpython-312-aarch64-linux-musl.so
amalgamation_ai/models/__init__.py
amalgamation_ai/models/blueprint.cpython-312-aarch64-linux-musl.so
amalgamation_ai/models/common.cpython-312-aarch64-linux-musl.so
amalgamation_ai/models/execution.cpython-312-aarch64-linux-musl.so
amalgamation_ai/resources/__init__.py
amalgamation_ai/resources/base.cpython-312-aarch64-linux-musl.so
amalgamation_ai/resources/executions.cpython-312-aarch64-linux-musl.so
amalgamation_ai/resources/generations.cpython-312-aarch64-linux-musl.so
amalgamation_ai/resources/uploads.cpython-312-aarch64-linux-musl.so
amalgamation_ai/util/__init__.py
amalgamation_ai/util/file_handler.cpython-312-aarch64-linux-musl.so
amalgamation_ai/util/helpers.cpython-312-aarch64-linux-musl.so
amalgamation_ai/util/poller.cpython-312-aarch64-linux-musl.so
amalgamation_ai/util/validators.cpython-312-aarch64-linux-musl.so
amalgamation_api_client/__init__.py
amalgamation_api_client/client.cpython-312-aarch64-linux-musl.so
amalgamation_ai_sdk-0.0.1.dist-info/METADATA
amalgamation_ai_sdk-0.0.1.dist-info/WHEEL
amalgamation_ai_sdk-0.0.1.dist-info/top_level.txt
amalgamation_ai_sdk-0.0.1.dist-info/RECORD
