Metadata-Version: 2.1
Name: amalgamation-ai-sdk
Version: 0.0.1
Summary: Official Python SDK for AmalgamationAI - AI Vision Blueprint Platform
Author: AmalgamationAI Team
Keywords: ai,computer-vision,amalgamation
Classifier: Intended Audience :: Developers
Classifier: Programming Language :: Python :: 3
Classifier: Programming Language :: Python :: 3.8
Requires-Python: >=3.8
Requires-Dist: httpx
Requires-Dist: pydantic
Requires-Dist: python-dateutil
Requires-Dist: pyyaml
Requires-Dist: typing-extensions
Provides-Extra: dev
Requires-Dist: black>=23.7.0; extra == "dev"
Requires-Dist: mypy>=1.4.0; extra == "dev"
Requires-Dist: pytest>=7.4.0; extra == "dev"
Requires-Dist: pytest-asyncio>=0.21.0; extra == "dev"
Requires-Dist: pytest-cov>=4.1.0; extra == "dev"
Requires-Dist: pytest-mock>=3.11.0; extra == "dev"
Requires-Dist: respx>=0.20.0; extra == "dev"
Requires-Dist: ruff>=0.1.0; extra == "dev"
Provides-Extra: docs
Requires-Dist: myst-parser>=2.0.0; extra == "docs"
Requires-Dist: sphinx>=7.0.0; extra == "docs"
Requires-Dist: sphinx-autodoc-typehints>=1.24.0; extra == "docs"
Requires-Dist: sphinx-rtd-theme>=1.3.0; extra == "docs"
